pyqt6_plugins/__init__.py
pyqt6_plugins/_version.py
pyqt6_plugins/examplebutton.py
pyqt6_plugins/examplebuttonplugin.py
pyqt6_plugins/utilities.py
pyqt6_plugins/Qt/plugins/libpyqt6qmlplugin.so
pyqt6_plugins/Qt/plugins/designer/libpyqt6.so
pyqt6_plugins/badplugin/__init__.py
pyqt6_plugins/badplugin/badwidgetplugin.py
pyqt6_plugins/examples/__init__.py
pyqt6_plugins/examples/exampleqmlitem.py
pyqt6_plugins/examples/exampleqmlitemplugin.py
pyqt6_plugins/examples/libpyqt6qmlplugin.so
pyqt6_plugins/examples/qmlapp.qml
pyqt6_plugins/examples/qmldir
pyqt6_plugins/examples/qmltest.qml
pyqt6_plugins/tests/__init__.py
pyqt6_plugins/tests/test_plugins.py
pyqt6_plugins/tests/testbutton.py
pyqt6_plugins/tests/testbuttonplugin.py
pyqt6_plugins-6.3.1.2.3.dist-info/COPYING
pyqt6_plugins-6.3.1.2.3.dist-info/METADATA
pyqt6_plugins-6.3.1.2.3.dist-info/WHEEL
pyqt6_plugins-6.3.1.2.3.dist-info/top_level.txt
pyqt6_plugins-6.3.1.2.3.dist-info/RECORD
