Metadata-Version: 2.1
Name: pyqt6-plugins
Version: 6.3.1.2.3
Summary: PyQt Designer and QML plugins
Home-page: https://github.com/altendky/pyqt-plugins
Author: Kyle Altendorf
Author-email: sda@fstab.net
License: GPLv3
Classifier: Development Status :: 4 - Beta
Classifier: Intended Audience :: Developers
Classifier: License :: OSI Approved :: GNU General Public License v3 (GPLv3)
Classifier: Operating System :: POSIX :: Linux
Classifier: Operating System :: MacOS :: MacOS X
Classifier: Operating System :: Microsoft :: Windows
Classifier: Programming Language :: Python :: 3
Classifier: Programming Language :: Python :: 3.5
Classifier: Programming Language :: Python :: 3.6
Classifier: Programming Language :: Python :: 3.7
Classifier: Programming Language :: Python :: 3.8
Classifier: Programming Language :: Python :: 3.9
Classifier: Topic :: Software Development
Classifier: Topic :: Utilities
Requires-Python: >=3.7
License-File: COPYING
Requires-Dist: click
Requires-Dist: pyqt6 (==6.3.1)
Requires-Dist: pyqt6-qt6 (==6.3.2)
Requires-Dist: qt6-tools (<6.3.2.2,>=6.3.2.1.2)
